{"id":"129","name":"Sum Root to Leaf Numbers","link":"/problems/sum-root-to-leaf-numbers/","ac":"31.5%","difficulty":"Medium","description":"<p>Given a binary tree containing digits from <code>0-9</code> only, each root-to-leaf path could represent a number.</p><p>An example is the root-to-leaf path <code>1-&gt;2-&gt;3</code> which represents the number <code>123</code>.</p><p>Find the total sum of all root-to-leaf numbers.</p><p>For example,\r\n<pre>\r\n    1\r\n   / \\\r\n  2   3\r\n</pre>\r\n</p><p>\r\nThe root-to-leaf path <code>1-&gt;2</code> represents the number <code>12</code>.<br>\r\nThe root-to-leaf path <code>1-&gt;3</code> represents the number <code>13</code>.\r\n</p><p>\r\nReturn the sum = 12 + 13 = <code>25</code>.\r\n</p>"}